vk_dark_library/VKBotLongPoll.py
vk_dark_library/VKCommandHandler.py
vk_dark_library/VKDebugMode.py
vk_dark_library/VKErrorLibrary.py
vk_dark_library/VKUtils.py
vk_dark_library/__init__.py
vk_dark_library-1.0.6.dist-info/LICENSE
vk_dark_library-1.0.6.dist-info/METADATA
vk_dark_library-1.0.6.dist-info/WHEEL
vk_dark_library-1.0.6.dist-info/top_level.txt
vk_dark_library-1.0.6.dist-info/RECORD
