Metadata-Version: 2.1
Name: vk-dark-library
Version: 1.0.6
Summary: Быстрое и удобное создание ботов в вк. Пока только LongPoll.
Home-page: https://github.com/DarkLorianPrime/vk_library
Author: Darklorian (Aleksander Kasimov)
Author-email: lolpokens@mail.ru
License: Apache License, Version 2.0, see LICENSE file
Platform: UNKNOWN
Requires-Python: >3.6
License-File: LICENSE
Requires-Dist: requests (>=2)
